localorm/__init__.py
localorm/_core.py
localorm-0.1.12.dist-info/METADATA
localorm-0.1.12.dist-info/WHEEL
localorm-0.1.12.dist-info/top_level.txt
localorm-0.1.12.dist-info/RECORD
