Metadata-Version: 2.4
Name: localorm
Version: 0.1.12
Summary: local orm
Project-URL: Homepage, https://github.com/jwzhouyy/localorm
Requires-Python: >=3.12
Requires-Dist: pydantic>=2.12.3
Requires-Dist: sqlalchemy>=2.0.44
Requires-Dist: sqlmodel>=0.0.27
